[{
        "title": "ခေအၒ",
        "image": "https://api.androidhive.info/json/movies/1.jpg",
        "rating": 8.3,
        "releaseYear": 2014,
        "genre": ["Action", "Drama", "Sci-Fi"]
    },
    {
        "title": "ရက္သြတ္",
        "image": "https://api.androidhive.info/json/movies/2.jpg",
        "rating": 8,
        "releaseYear": 2009,
        "genre": ["Action", "Sci-Fi", "Thriller"]
    },
    {
        "title": "ယူၒလꩻ",
        "image": "https://api.androidhive.info/json/movies/3.jpg",
        "rating": 6.3,
        "releaseYear": 2014,
        "genre": ["Action", "Adventure", "Sci-Fi"]
    },
    {
        "title": "သဲင္ꩻလမ္း ",
        "image": "https://api.androidhive.info/json/movies/4.jpg",
        "rating": 8.4,
        "releaseYear": 2014,
        "genre": ["Action", "Sci-Fi", "Thriller"]
    },
    {
        "title": "ယူၒ",
        "image": "https://api.androidhive.info/json/movies/5.jpg",
        "rating": 7.8,
        "releaseYear": 2004,
        "genre": ["Drama", "Thriller"]
    },
    {
        "title": "ညာꩻေနေန ",
        "image": "https://api.androidhive.info/json/movies/6.jpg",
        "rating": 7.7,
        "releaseYear": 2003,
        "genre": ["Action", "Drama", "History"]
    },
    {
        "title": "နင္ၒခံꩻေပၒ ",
        "image": "https://api.androidhive.info/json/movies/7.jpg",
        "rating": 7.3,
        "releaseYear": 2014,
        "genre": ["Action", "Adventure", "Fantasy"]
    },
    {
        "title": "သꩻတသဥ္ ",
        "image": "https://api.androidhive.info/json/movies/8.jpg",
        "rating": 7.9,
        "releaseYear": 2010,
        "genre": ["Action", "Drama", "Sci-Fi"]
    },
    {
        "title": "ခမ္းခါ ",
        "image": "https://api.androidhive.info/json/movies/9.jpg",
        "rating": 8.3,
        "releaseYear": 2013,
        "genre": ["Animation", "Comedy", "Family"]
    },
    {
        "title": "သဲင္ꩻလမ္း ",
        "image": "https://api.androidhive.info/json/movies/10.jpg",
        "rating": 6.7,
        "releaseYear": 2009,
        "genre": ["Horror", "Thriller"]
    },
    {
        "title": "ယိုတျဖာꩻ ",
        "image": "https://api.androidhive.info/json/movies/11.jpg",
        "rating": 7.6,
        "releaseYear": 2013,
        "genre": ["Animation", "Comedy", "Family"]
    },
    {
        "title": "ကံၒတရာꩻ ",
        "image": "https://api.androidhive.info/json/movies/12.jpg",
        "rating": 8.2,
        "releaseYear": 2003,
        "genre": ["Action", "Crime"]
    },
    {
        "title": "ထီၒေန ",
        "image": "https://api.androidhive.info/json/movies/13.jpg",
        "rating": 7.2,
        "releaseYear": 1998,
        "genre": ["Animation", "Adventure", "Comedy"]
    },
    {
        "title": "ယြယြက ",
        "image": "https://api.androidhive.info/json/movies/14.jpg",
        "rating": 8.9,
        "releaseYear": 1972,
        "genre": ["Comedy"]
    },
    {
        "title": "ညာꩻနင္ၒထုဲင္ၒခမ္း",
        "image": "https://api.androidhive.info/json/movies/15.jpg",
        "rating": 8.2,
        "releaseYear": 2010,
        "genre": ["Animation", "Adventure", "Family"]
    }]
